[{"children":[],"properties":{"workUnloadTim":247.76,"time":432.46,"wgt":112988,"noworkShipTim":0,"noworkPortTim":0,"CARGO_KIND_NAM":"金属矿石","weatherTim":0,"noworkCargoTim":0,"workOtherTim":0,"noworkOtherTim":0}},{"children":[],"properties":{"workUnloadTim":3279.48,"time":5645.7,"wgt":1267854,"noworkShipTim":0,"noworkPortTim":0,"CARGO_KIND_NAM":"煤炭及制品","weatherTim":9,"noworkCargoTim":21,"workOtherTim":0,"noworkOtherTim":0}},{"children":[],"properties":{"workUnloadTim":16.04,"time":84.04,"wgt":0,"noworkShipTim":0,"noworkPortTim":0,"CARGO_KIND_NAM":"机械、设备、电器","weatherTim":0,"noworkCargoTim":0,"workOtherTim":0,"noworkOtherTim":0}},{"children":[],"properties":{"workUnloadTim":42.54,"time":52.04,"wgt":300,"noworkShipTim":0,"noworkPortTim":0,"CARGO_KIND_NAM":"有色金属","weatherTim":0,"noworkCargoTim":0,"workOtherTim":0,"noworkOtherTim":0}},{"children":[],"properties":{"workUnloadTim":1259.34,"time":1704.98,"wgt":318902,"noworkShipTim":0,"noworkPortTim":0,"CARGO_KIND_NAM":"矿物性建筑材料","weatherTim":0,"noworkCargoTim":0,"workOtherTim":0,"noworkOtherTim":0}},{"children":[],"properties":{"workUnloadTim":646.96,"time":1145.92,"wgt":137974,"noworkShipTim":0,"noworkPortTim":0,"CARGO_KIND_NAM":"水泥","weatherTim":0,"noworkCargoTim":0,"workOtherTim":0,"noworkOtherTim":0}},{"children":[],"properties":{"workUnloadTim":1627.22,"time":2428.9,"wgt":201390,"noworkShipTim":0,"noworkPortTim":0,"CARGO_KIND_NAM":"化学肥料及农药","weatherTim":5,"noworkCargoTim":0,"workOtherTim":9,"noworkOtherTim":0}},{"children":[],"properties":{"workUnloadTim":660.56,"time":985.4,"wgt":39358,"noworkShipTim":0,"noworkPortTim":0,"CARGO_KIND_NAM":"粮食","weatherTim":0,"noworkCargoTim":0,"workOtherTim":0,"noworkOtherTim":0}},{"children":[],"properties":{"workUnloadTim":271.46,"time":501.62,"wgt":50686,"noworkShipTim":0,"noworkPortTim":0,"CARGO_KIND_NAM":"化工原料及制品","weatherTim":0,"noworkCargoTim":0,"workOtherTim":0,"noworkOtherTim":0}},{"children":[],"properties":{"workUnloadTim":1763.12,"time":3258.02,"wgt":388668,"noworkShipTim":0,"noworkPortTim":0,"CARGO_KIND_NAM":"石油、天然气及制品","weatherTim":0,"noworkCargoTim":0,"workOtherTim":0,"noworkOtherTim":0}},{"children":[],"properties":{"workUnloadTim":1158.58,"time":2833.44,"wgt":3334,"noworkShipTim":0,"noworkPortTim":0,"CARGO_KIND_NAM":"其它货类","weatherTim":33,"noworkCargoTim":0,"workOtherTim":0,"noworkOtherTim":0}},{"children":[],"properties":{"workUnloadTim":191.08,"time":197.58,"wgt":5128,"noworkShipTim":0,"noworkPortTim":0,"CARGO_KIND_NAM":"木材","weatherTim":0,"noworkCargoTim":0,"workOtherTim":0,"noworkOtherTim":0}},{"children":[],"properties":{"workUnloadTim":1653.96,"time":2497.24,"wgt":1056066,"noworkShipTim":0,"noworkPortTim":0,"CARGO_KIND_NAM":"非金属矿石","weatherTim":12,"noworkCargoTim":0,"workOtherTim":0,"noworkOtherTim":0}},{"children":[],"properties":{"workUnloadTim":400.48,"time":548.48,"wgt":22800,"noworkShipTim":0,"noworkPortTim":0,"CARGO_KIND_NAM":"盐","weatherTim":14,"noworkCargoTim":0,"workOtherTim":0,"noworkOtherTim":0}},{"children":[],"properties":{"workUnloadTim":148.2,"time":150.2,"wgt":20968,"noworkShipTim":0,"noworkPortTim":0,"CARGO_KIND_NAM":"农、林、牧、渔业产品","weatherTim":0,"noworkCargoTim":0,"workOtherTim":0,"noworkOtherTim":0}}]